{"nodes": [{"id": "app_lib_adaptiveengine_ts", "label": "adaptiveEngine.ts", "file_type": "code", "source_file": "app\\lib\\adaptiveEngine.ts", "source_location": "L1"}, {"id": "adaptiveengine_adaptiveengine", "label": "AdaptiveEngine", "file_type": "code", "source_file": "app\\lib\\adaptiveEngine.ts", "source_location": "L24"}, {"id": "adaptiveengine_adaptiveengine_getinitialsettings", "label": ".getInitialSettings()", "file_type": "code", "source_file": "app\\lib\\adaptiveEngine.ts", "source_location": "L26"}, {"id": "adaptiveengine_adaptiveengine_evaluatereflexperformance", "label": ".evaluateReflexPerformance()", "file_type": "code", "source_file": "app\\lib\\adaptiveEngine.ts", "source_location": "L31"}, {"id": "adaptiveengine_adaptiveengine_evaluatememoryperformance", "label": ".evaluateMemoryPerformance()", "file_type": "code", "source_file": "app\\lib\\adaptiveEngine.ts", "source_location": "L62"}], "edges": [{"source": "app_lib_adaptiveengine_ts", "target": "adaptiveengine_adaptiveengine", "relation": "contains", "confidence": "EXTRACTED", "source_file": "app\\lib\\adaptiveEngine.ts", "source_location": "L24", "weight": 1.0}, {"source": "adaptiveengine_adaptiveengine", "target": "adaptiveengine_adaptiveengine_getinitialsettings", "relation": "method", "confidence": "EXTRACTED", "source_file": "app\\lib\\adaptiveEngine.ts", "source_location": "L26", "weight": 1.0}, {"source": "adaptiveengine_adaptiveengine", "target": "adaptiveengine_adaptiveengine_evaluatereflexperformance", "relation": "method", "confidence": "EXTRACTED", "source_file": "app\\lib\\adaptiveEngine.ts", "source_location": "L31", "weight": 1.0}, {"source": "adaptiveengine_adaptiveengine", "target": "adaptiveengine_adaptiveengine_evaluatememoryperformance", "relation": "method", "confidence": "EXTRACTED", "source_file": "app\\lib\\adaptiveEngine.ts", "source_location": "L62", "weight": 1.0}], "raw_calls": [{"caller_nid": "adaptiveengine_adaptiveengine_evaluatereflexperformance", "callee": "max", "source_file": "app\\lib\\adaptiveEngine.ts", "source_location": "L43"}, {"caller_nid": "adaptiveengine_adaptiveengine_evaluatereflexperformance", "callee": "max", "source_file": "app\\lib\\adaptiveEngine.ts", "source_location": "L44"}, {"caller_nid": "adaptiveengine_adaptiveengine_evaluatereflexperformance", "callee": "max", "source_file": "app\\lib\\adaptiveEngine.ts", "source_location": "L48"}, {"caller_nid": "adaptiveengine_adaptiveengine_evaluatereflexperformance", "callee": "min", "source_file": "app\\lib\\adaptiveEngine.ts", "source_location": "L53"}, {"caller_nid": "adaptiveengine_adaptiveengine_evaluatereflexperformance", "callee": "min", "source_file": "app\\lib\\adaptiveEngine.ts", "source_location": "L54"}, {"caller_nid": "adaptiveengine_adaptiveengine_evaluatereflexperformance", "callee": "max", "source_file": "app\\lib\\adaptiveEngine.ts", "source_location": "L57"}, {"caller_nid": "adaptiveengine_adaptiveengine_evaluatememoryperformance", "callee": "max", "source_file": "app\\lib\\adaptiveEngine.ts", "source_location": "L73"}, {"caller_nid": "adaptiveengine_adaptiveengine_evaluatememoryperformance", "callee": "max", "source_file": "app\\lib\\adaptiveEngine.ts", "source_location": "L74"}]}